pyspector/__init__.py
pyspector/_rust_core.cpython-310-x86_64-linux-gnu.so
pyspector/cli.py
pyspector/config.py
pyspector/plugin_system.py
pyspector/reporting.py
pyspector/triage.py
pyspector/_rust_core/Cargo.toml
pyspector/_rust_core/src/ast_parser.rs
pyspector/_rust_core/src/issues.rs
pyspector/_rust_core/src/lib.rs
pyspector/_rust_core/src/rules.rs
pyspector/_rust_core/src/analysis/ast_analysis.rs
pyspector/_rust_core/src/analysis/config_analysis.rs
pyspector/_rust_core/src/analysis/mod.rs
pyspector/_rust_core/src/analysis/taint_analysis.rs
pyspector/_rust_core/src/graph/call_graph_builder.rs
pyspector/_rust_core/src/graph/cfg_builder.rs
pyspector/_rust_core/src/graph/mod.rs
pyspector/_rust_core/src/graph/representation.rs
pyspector/rules/__init__.py
pyspector/rules/built-in-rules-ai.toml
pyspector/rules/built-in-rules.toml
pyspector-0.1.5.dist-info/METADATA
pyspector-0.1.5.dist-info/WHEEL
pyspector-0.1.5.dist-info/entry_points.txt
pyspector-0.1.5.dist-info/top_level.txt
pyspector-0.1.5.dist-info/RECORD
pyspector-0.1.5.dist-info/licenses/LICENSE
pyspector-0.1.5.dist-info/licenses/NOTICE.md
