Metadata-Version: 2.4
Name: pyspector
Version: 0.1.5
Summary: A high-performance, security-focused static analysis tool for Python, powered by Rust.
Author: ParzivalHack
License: MIT
Keywords: static analysis security python rust
Requires-Python: >=3.8
License-File: LICENSE
License-File: NOTICE.md
Requires-Dist: click>=8.0
Requires-Dist: toml>=0.10
Requires-Dist: requests>=2.25
Requires-Dist: sarif-om>=1.0
Requires-Dist: jinja2>=3.0
Requires-Dist: textual>=0.60
Requires-Dist: importlib_resources; python_version < "3.9"
Dynamic: author
Dynamic: description
Dynamic: description-content-type
Dynamic: keywords
Dynamic: license
Dynamic: license-file
Dynamic: requires-dist
Dynamic: requires-python
Dynamic: summary
